vive_tracker_apiserver/__init__.py
vive_tracker_apiserver/__main__.py
vive_tracker_apiserver/apiserver/__init__.py
vive_tracker_apiserver/apiserver/app.py
vive_tracker_apiserver/apiserver/main.py
vive_tracker_apiserver/apiserver/server.py
vive_tracker_apiserver/client/Client.py
vive_tracker_apiserver/client/__init__.py
vive_tracker_apiserver/cmd/__init__.py
vive_tracker_apiserver/cmd/configure.py
vive_tracker_apiserver/cmd/list_devices.py
vive_tracker_apiserver/cmd/test_server.py
vive_tracker_apiserver/cmd/test_visualize.py
vive_tracker_apiserver/common/Config.py
vive_tracker_apiserver/common/__init__.py
vive_tracker_apiserver/common/functional.py
vive_tracker_apiserver/grpc/__init__.py
vive_tracker_apiserver/grpc/tracker_packet_pb2.py
vive_tracker_apiserver/grpc/tracker_packet_pb2_grpc.py
vive_tracker_apiserver/third_party/__init__.py
vive_tracker_apiserver/third_party/triad_openvr/controller_test.py
vive_tracker_apiserver/third_party/triad_openvr/tracker_test.py
vive_tracker_apiserver/third_party/triad_openvr/triad_openvr.py
vive_tracker_apiserver/third_party/triad_openvr/udp_emitter.py
vive_tracker_apiserver/vr/__init__.py
vive_tracker_apiserver-0.0.7.dist-info/METADATA
vive_tracker_apiserver-0.0.7.dist-info/WHEEL
vive_tracker_apiserver-0.0.7.dist-info/top_level.txt
vive_tracker_apiserver-0.0.7.dist-info/RECORD
