Metadata-Version: 2.1
Name: vive-tracker-apiserver
Version: 0.0.7
Summary: Vive Tracker APIServer
Author: davidliyutong
Author-email: davidliyutong@sjtu.edu.cn
Requires-Python: >=3.7
Requires-Dist: openvr
Requires-Dist: numpy
Requires-Dist: grpcio
Requires-Dist: grpcio-tools
Requires-Dist: py-cli-interaction
Requires-Dist: pyyaml
Requires-Dist: open3d
Requires-Dist: tqdm
Requires-Dist: transforms3d
